PySlice_Tools/__init__.py
PySlice_Tools/app.py
PySlice_Tools/command_help.json
PySlice_Tools/cube.py
PySlice_Tools/gui.py
PySlice_Tools/state.py
PySlice_Tools/support.py
PySlice_Tools/slice/__init__.py
PySlice_Tools/slice/_slice.cpp
PySlice_Tools/slice/_slice.o
PySlice_Tools/slice/_slice.so
PySlice_Tools-1.5.data/data/PySlice_Tools/_slice.cpp
PySlice_Tools-1.5.data/data/PySlice_Tools/_slice.o
PySlice_Tools-1.5.data/data/PySlice_Tools/_slice.so
PySlice_Tools-1.5.data/data/PySlice_Tools/command_help.json
PySlice_Tools-1.5.dist-info/METADATA
PySlice_Tools-1.5.dist-info/WHEEL
PySlice_Tools-1.5.dist-info/entry_points.txt
PySlice_Tools-1.5.dist-info/top_level.txt
PySlice_Tools-1.5.dist-info/RECORD
