Metadata-Version: 2.1
Name: PySlice-Tools
Version: 1.5
Summary: UNKNOWN
Home-page: UNKNOWN
License: UNKNOWN
Platform: UNKNOWN
Requires-Dist: matplotlib
Requires-Dist: wheel
